pyergo/__init__.py
pyxsb/__init__.py
vital_logic-0.1.0.dist-info/LICENSE
vital_logic-0.1.0.dist-info/METADATA
vital_logic-0.1.0.dist-info/WHEEL
vital_logic-0.1.0.dist-info/top_level.txt
vital_logic-0.1.0.dist-info/RECORD
