Metadata-Version: 2.1
Name: vital-logic
Version: 0.1.0
Summary: Vital Logic
Home-page: https://github.com/vital-ai/vital-logic-python
Author: Marc Hadfield
Author-email: marc@vital.ai
License: Apache License 2.0
Classifier: Programming Language :: Python :: 3.10
Classifier: License :: OSI Approved :: Apache Software License
Classifier: Operating System :: OS Independent
Requires-Python: >=3.10
License-File: LICENSE
Requires-Dist: vital-ai-vitalsigns>=0.1.27
Requires-Dist: six
Requires-Dist: pyyaml
